README.rst
setup.cfg
setup.py
sf_tools/__init__.py
sf_tools/info.py
sf_tools.egg-info/PKG-INFO
sf_tools.egg-info/SOURCES.txt
sf_tools.egg-info/dependency_links.txt
sf_tools.egg-info/requires.txt
sf_tools.egg-info/top_level.txt
sf_tools/image/__init__.py
sf_tools/image/distort.py
sf_tools/image/quality.py
sf_tools/image/shape.py
sf_tools/image/stamp.py
sf_tools/image/stats.py