Metadata-Version: 1.1
Name: sf-tools
Version: 2.0.0
Summary: Tools for image analysis, signal processing and statistics.
Home-page: https://github.com/sfarrens/sf_tools
Author: sfarrens
Author-email: samuel.farrens@cea.fr
License: MIT
Download-URL: https://github.com/sfarrens/sf_tools
Platform: UNKNOWN
